blendfig/__init__.py
blendfig/blendfig_assets.blend
blendfig/axes/axes.py
blendfig/bounds/bounds.py
blendfig/geometry/geometry.py
blendfig/materials/colors.py
blendfig/materials/materials.py
blendfig/nodes/nodes.py
blendfig/tools/functions.py
blendfig/traces/bar.py
blendfig/traces/scatter.py
blendfig/traces/surface.py
blendfig/traces/trace.py
build/lib/blendfig/__init__.py
build/lib/blendfig/axes/axes.py
build/lib/blendfig/bounds/bounds.py
build/lib/blendfig/geometry/geometry.py
build/lib/blendfig/materials/colors.py
build/lib/blendfig/materials/materials.py
build/lib/blendfig/nodes/nodes.py
build/lib/blendfig/tools/functions.py
build/lib/blendfig/traces/bar.py
build/lib/blendfig/traces/scatter.py
build/lib/blendfig/traces/surface.py
build/lib/blendfig/traces/trace.py
blendfig-0.1.4.dist-info/LICENSE.txt
blendfig-0.1.4.dist-info/METADATA
blendfig-0.1.4.dist-info/WHEEL
blendfig-0.1.4.dist-info/top_level.txt
blendfig-0.1.4.dist-info/RECORD
