Metadata-Version: 2.1
Name: blendfig
Version: 0.1.4
Summary: Python plotting library for Blender
Home-page: https://github.com/stanrusak/blendfig
Author: Stanislav Rusak
Author-email: stanislav.rusak@gmail.com
License: GPLv3+
Classifier: License :: OSI Approved :: GNU General Public License v3 or later (GPLv3+)
Classifier: Programming Language :: Python :: 3
Classifier: Programming Language :: Python :: 3.9
Classifier: Development Status :: 3 - Alpha
Classifier: Topic :: Scientific/Engineering :: Visualization
Classifier: Topic :: Multimedia :: Graphics :: 3D Modeling
License-File: LICENSE.txt
